token_usage_metrics/__init__.py
token_usage_metrics/client.py
token_usage_metrics/config.py
token_usage_metrics/errors.py
token_usage_metrics/logging.py
token_usage_metrics/models.py
token_usage_metrics/queue.py
token_usage_metrics/uv.lock
token_usage_metrics/backends/__init__.py
token_usage_metrics/backends/base.py
token_usage_metrics/backends/mongodb.py
token_usage_metrics/backends/postgres.py
token_usage_metrics/backends/redis.py
token_usage_metrics/backends/supabase.py
token_usage_metrics-0.1.1.dist-info/METADATA
token_usage_metrics-0.1.1.dist-info/WHEEL
token_usage_metrics-0.1.1.dist-info/licenses/LICENSE
token_usage_metrics-0.1.1.dist-info/RECORD
