Metadata-Version: 2.4
Name: token-usage-metrics
Version: 0.1.1
Summary: Async LLM/embedding token usage tracking with multi-backend support (Redis, Postgres/Supabase, MongoDB)
License-File: LICENSE
Requires-Python: >=3.13
Requires-Dist: asyncpg>=0.30.0
Requires-Dist: motor>=3.7.1
Requires-Dist: pydantic-settings>=2.4.0
Requires-Dist: pydantic>=2.7.0
Requires-Dist: redis>=7.0.1
Requires-Dist: tenacity>=9.0.0
Requires-Dist: typing-extensions>=4.12.0
Provides-Extra: all
Requires-Dist: asyncpg>=0.29.0; extra == 'all'
Requires-Dist: motor>=3.4.0; extra == 'all'
Requires-Dist: redis>=5.0.0; extra == 'all'
Provides-Extra: dev
Requires-Dist: mypy>=1.11.0; extra == 'dev'
Requires-Dist: ruff>=0.6.0; extra == 'dev'
Provides-Extra: logging
Requires-Dist: structlog>=24.2.0; extra == 'logging'
Provides-Extra: mongo
Requires-Dist: motor>=3.4.0; extra == 'mongo'
Provides-Extra: postgres
Requires-Dist: asyncpg>=0.29.0; extra == 'postgres'
Provides-Extra: redis
Requires-Dist: redis>=5.0.0; extra == 'redis'
Provides-Extra: supabase
Requires-Dist: asyncpg>=0.29.0; extra == 'supabase'
Provides-Extra: test
Requires-Dist: anyio>=4.4.0; extra == 'test'
Requires-Dist: fakeredis[lua]>=2.23.0; extra == 'test'
Requires-Dist: pytest-asyncio>=0.23.0; extra == 'test'
Requires-Dist: pytest-cov>=5.0.0; extra == 'test'
Requires-Dist: pytest>=8.3.0; extra == 'test'
